momento_signer/__init__.py
momento_signer/momento_signer.py
momento_signer-0.2.2.dist-info/METADATA
momento_signer-0.2.2.dist-info/WHEEL
momento_signer-0.2.2.dist-info/LICENSE
momento_signer-0.2.2.dist-info/RECORD
