Metadata-Version: 2.1
Name: momento-signer
Version: 0.2.2
Summary: Signed URL SDK for Momento
Home-page: https://gomomento.com
License: Apache-2.0
Keywords: Momento,caching,key-value store,serverless
Author: Momento
Author-email: hello@momentohq.com
Requires-Python: >=3.7,<4.0
Classifier: Development Status :: 3 - Alpha
Classifier: Environment :: Console
Classifier: Intended Audience :: Developers
Classifier: License :: OSI Approved :: Apache Software License
Classifier: Natural Language :: English
Classifier: Operating System :: OS Independent
Classifier: Programming Language :: Python :: 3
Classifier: Programming Language :: Python :: 3.7
Classifier: Programming Language :: Python :: 3.8
Classifier: Programming Language :: Python :: 3.9
Classifier: Programming Language :: Python :: 3.10
Classifier: Programming Language :: Python :: 3.11
Classifier: Topic :: Internet
Classifier: Typing :: Typed
Requires-Dist: cryptography (==3.4.8)
Requires-Dist: pyjwt (==2.4.0)
Project-URL: Documentation, https://docs.momentohq.com/
Project-URL: Repository, https://github.com/momentohq/client-sdk-python-signed-urls
